<?xml version="1.0" encoding="UTF-8"?>
<tv>
<channel><tabIndex></tabIndex><title>12 TV Parma</title></channel>
<channel><tabIndex></tabIndex><title>2M Monde</title></channel>
<channel><tabIndex></tabIndex><title>360°</title></channel>
<channel><tabIndex></tabIndex><title>Abu Dhabi Drama</title></channel>
<channel><tabIndex></tabIndex><title>Abu Dhabi TV</title></channel>
<channel><tabIndex></tabIndex><title>Aden TV</title></channel>
<channel><tabIndex></tabIndex><title>Ajyal TV</title></channel>
<channel><tabIndex></tabIndex><title>Al Aoula</title></channel>
<channel><tabIndex></tabIndex><title>Al Aoula Laayoune</title></channel>
<channel><tabIndex></tabIndex><title>Al Dafrah TV</title></channel>
<channel><tabIndex></tabIndex><title>Al Emarat TV</title></channel>
<channel><tabIndex></tabIndex><title>Al Ittihad</title></channel>
<channel><tabIndex></tabIndex><title>Al Khalij</title></channel>
<channel><tabIndex></tabIndex><title>Al Maghribia</title></channel>
<channel><tabIndex></tabIndex><title>Al Mamlaka TV</title></channel>
<channel><tabIndex></tabIndex><title>Al Rafidain HQ</title></channel>
<channel><tabIndex></tabIndex><title>Al Rasheed</title></channel>
<channel><tabIndex></tabIndex><title>Al Rayyan</title></channel>
<channel><tabIndex></tabIndex><title>Al Saudiya</title></channel>
<channel><tabIndex></tabIndex><title>Al Sharq</title></channel>
<channel><tabIndex></tabIndex><title>Al Sharqiya</title></channel>
<channel><tabIndex></tabIndex><title>Al Wousta TV</title></channel>
<channel><tabIndex></tabIndex><title>Alfajer Tv HD 2</title></channel>
<channel><tabIndex></tabIndex><title>Alhayat TV</title></channel>
<channel><tabIndex></tabIndex><title>Amman TV</title></channel>
<channel><tabIndex></tabIndex><title>ARB</title></channel>
<channel><tabIndex></tabIndex><title>Assadissa</title></channel>
<channel><tabIndex></tabIndex><title>Assyrian ANB</title></channel>
<channel><tabIndex></tabIndex><title>Athaqafia (360p)</title></channel>
<channel><tabIndex></tabIndex><title>Bahrain International</title></channel>
<channel><tabIndex></tabIndex><title>Bahrain TV</title></channel>
<channel><tabIndex></tabIndex><title>Boss Brothers TV</title></channel>
<channel><tabIndex></tabIndex><title>Canal Macau</title></channel>
<channel><tabIndex></tabIndex><title>Canal Ricos</title></channel>
<channel><tabIndex></tabIndex><title>COM Brasil</title></channel>
<channel><tabIndex></tabIndex><title>Congo Planet Television</title></channel>
<channel><tabIndex></tabIndex><title>Dubai One</title></channel>
<channel><tabIndex></tabIndex><title>Dubai TV</title></channel>
<channel><tabIndex></tabIndex><title>Fail Army</title></channel>
<channel><tabIndex></tabIndex><title>FastWay</title></channel>
<channel><tabIndex></tabIndex><title>France 2</title></channel>
<channel><tabIndex></tabIndex><title>Future TV</title></channel>
<channel><tabIndex></tabIndex><title>Glewed TV</title></channel>
<channel><tabIndex></tabIndex><title>Hawas TV</title></channel>
<channel><tabIndex></tabIndex><title>IRIB TV3 (Farsiland)</title></channel>
<channel><tabIndex></tabIndex><title>Ishtar TV</title></channel>
<channel><tabIndex></tabIndex><title>Kurdistan TV</title></channel>
<channel><tabIndex></tabIndex><title>LBC International</title></channel>
<channel><tabIndex></tabIndex><title>MBC</title></channel>
<channel><tabIndex></tabIndex><title>MBC 4</title></channel>
<channel><tabIndex></tabIndex><title>MBC 5</title></channel>
<channel><tabIndex></tabIndex><title>MBC Bollywood</title></channel>
<channel><tabIndex></tabIndex><title>MBC Drama</title></channel>
<channel><tabIndex></tabIndex><title>MBC Iraq</title></channel>
<channel><tabIndex></tabIndex><title>MBC Masr 1</title></channel>
<channel><tabIndex></tabIndex><title>MBC Masr 2</title></channel>
<channel><tabIndex></tabIndex><title>MBC Persia</title></channel>
<channel><tabIndex></tabIndex><title>MKK Web TV</title></channel>
<channel><tabIndex></tabIndex><title>MusawaChannel</title></channel>
<channel><tabIndex></tabIndex><title>Noor Dubai</title></channel>
<channel><tabIndex></tabIndex><title>Oman TV</title></channel>
<channel><tabIndex></tabIndex><title>Oman TV Mubashir</title></channel>
<channel><tabIndex></tabIndex><title>ORF 1</title></channel>
<channel><tabIndex></tabIndex><title>Palestine Mubasher</title></channel>
<channel><tabIndex></tabIndex><title>Palestine Satellite Channel</title></channel>
<channel><tabIndex></tabIndex><title>Pop</title></channel>
<channel><tabIndex></tabIndex><title>Porto Canal</title></channel>
<channel><tabIndex></tabIndex><title>Qatar TV</title></channel>
<channel><tabIndex></tabIndex><title>Qatar TV 2</title></channel>
<channel><tabIndex></tabIndex><title>Right Now TV</title></channel>
<channel><tabIndex></tabIndex><title>Rotana Drama HD</title></channel>
<channel><tabIndex></tabIndex><title>Rotana+</title></channel>
<channel><tabIndex></tabIndex><title>RTP Açores</title></channel>
<channel><tabIndex></tabIndex><title>RTP Internacional</title></channel>
<channel><tabIndex></tabIndex><title>RTP Madeira</title></channel>
<channel><tabIndex></tabIndex><title>RTP África [not 24/7]</title></channel>
<channel><tabIndex></tabIndex><title>RTSH 1</title></channel>
<channel><tabIndex></tabIndex><title>Sahel TV</title></channel>
<channel><tabIndex></tabIndex><title>Sent TV Global Network</title></channel>
<channel><tabIndex></tabIndex><title>Syria Satellite Channel</title></channel>
<channel><tabIndex></tabIndex><title>Syria TV</title></channel>
<channel><tabIndex></tabIndex><title>Tamazight</title></channel>
<channel><tabIndex></tabIndex><title>TBD</title></channel>
<channel><tabIndex></tabIndex><title>Telemundo 44</title></channel>
<channel><tabIndex></tabIndex><title>TV Arapuan</title></channel>
<channel><tabIndex></tabIndex><title>TV Destak</title></channel>
<channel><tabIndex></tabIndex><title>TV Diário do Sertão</title></channel>
<channel><tabIndex></tabIndex><title>TV Sol</title></channel>
<channel><tabIndex></tabIndex><title>TV União DF</title></channel>
<channel><tabIndex></tabIndex><title>TV Verdes Campos</title></channel>
<channel><tabIndex></tabIndex><title>TVCI Paranaguá</title></channel>
<channel><tabIndex></tabIndex><title>TVG América</title></channel>
<channel><tabIndex></tabIndex><title>TVG Europa</title></channel>
<channel><tabIndex></tabIndex><title>TVM</title></channel>
<channel><tabIndex></tabIndex><title>TVM Internacional</title></channel>
<channel><tabIndex></tabIndex><title>TVR International</title></channel>
<channel><tabIndex></tabIndex><title>TVR Targu-Mures</title></channel>
<channel><tabIndex></tabIndex><title>TVRI Nasional</title></channel>
<channel><tabIndex></tabIndex><title>Viva Web TV</title></channel>
<channel><tabIndex></tabIndex><title>Yeeaah!</title></channel>
<channel><tabIndex></tabIndex><title>Zagros</title></channel>
<channel><tabIndex></tabIndex><title>Красная линия</title></channel>
<channel><tabIndex></tabIndex><title>Красная линия (480p)</title></channel>
<channel><tabIndex></tabIndex><title>МИР</title></channel>
<channel><tabIndex></tabIndex><title>Первый канал</title></channel>
<channel><tabIndex></tabIndex><title>Первый канал Евразия</title></channel>
<channel><tabIndex></tabIndex><title>Россия 1 +6</title></channel>
<channel><tabIndex></tabIndex><title>Россия 1 HD</title></channel>
<channel><tabIndex></tabIndex><title>СТВ</title></channel>
<channel><tabIndex></tabIndex><title>原住民電視</title></channel>
<channel><tabIndex></tabIndex><title>大愛1</title></channel>
<channel><tabIndex></tabIndex><title>大愛2</title></channel>
<channel><tabIndex></tabIndex><title>大立電視</title></channel>
<channel><tabIndex></tabIndex><title>澳視澳門</title></channel>
<channel><tabIndex></tabIndex><title>澳門-MACAU</title></channel>
<channel><tabIndex></tabIndex><title>香港開電視</title></channel>
</tv>